cliche/__init__.py
cliche/argparser.py
cliche/choice.py
cliche/docstring_to_help.py
cliche/import.log
cliche/install.py
cliche/install_generator.py
cliche/output.py
cliche/type_utils.py
cliche/types.py
cliche/using_underscore.py
cliche-0.10.124.dist-info/METADATA
cliche-0.10.124.dist-info/WHEEL
cliche-0.10.124.dist-info/entry_points.txt
cliche-0.10.124.dist-info/top_level.txt
cliche-0.10.124.dist-info/RECORD
